LICENSE.txt
README.md
pyproject.toml
setup.py
src/RecursionBook.egg-info/PKG-INFO
src/RecursionBook.egg-info/SOURCES.txt
src/RecursionBook.egg-info/dependency_links.txt
src/RecursionBook.egg-info/top_level.txt
src/recursionbook/__init__.py
src/recursionbook/__main__.py
src/recursionbook/floodfill.py