Metadata-Version: 2.1
Name: RecursionBook
Version: 0.1.0
Summary: The programs used in Al Sweigart's book, "The Recursive Book of Recursion".
Home-page: https://github.com/asweigart/recursionbook
Author: Al Sweigart
Author-email: al@inventwithpython.com
License: MIT
Platform: UNKNOWN
Classifier: License :: OSI Approved :: MIT License
Classifier: Programming Language :: Python
Classifier: Programming Language :: Python :: 3
Classifier: Programming Language :: Python :: 3.5
Classifier: Programming Language :: Python :: 3.6
Classifier: Programming Language :: Python :: 3.7
Classifier: Programming Language :: Python :: 3.8
Classifier: Programming Language :: Python :: 3.9
